llm_deepseek.py
llm_deepseek_xtreme-0.2.2.dist-info/licenses/LICENSE
llm_deepseek_xtreme-0.2.2.dist-info/METADATA
llm_deepseek_xtreme-0.2.2.dist-info/WHEEL
llm_deepseek_xtreme-0.2.2.dist-info/entry_points.txt
llm_deepseek_xtreme-0.2.2.dist-info/top_level.txt
llm_deepseek_xtreme-0.2.2.dist-info/RECORD
