Metadata-Version: 2.4
Name: llm-deepseek-xtreme
Version: 0.2.2
Summary: LLM access to DeepSeek's API
Author: Nick Mystic
License: MIT License
Project-URL: Homepage, https://github.com/ghostofpokemon/llm-deepseek
Project-URL: Changelog, https://github.com/ghostofpokemon/llm-deepseek/blob/main/CHANGELOG.md
Project-URL: Issues, https://github.com/ghostofpokemon/llm-deepseek/issues
Project-URL: CI, https://github.com/ghostofpokemon/llm-deepseek/actions
Classifier: License :: OSI Approved :: Apache Software License
Requires-Python: >=3.8
License-File: LICENSE
Requires-Dist: llm
Requires-Dist: httpx
Requires-Dist: rich
Provides-Extra: test
Requires-Dist: pytest; extra == "test"
Requires-Dist: pytest-httpx; extra == "test"
Dynamic: license-file
